LICENSE.txt
README.md
setup.cfg
setup.py
tensorflow3d/__init__.py
tensorflow3d.egg-info/PKG-INFO
tensorflow3d.egg-info/SOURCES.txt
tensorflow3d.egg-info/dependency_links.txt
tensorflow3d.egg-info/requires.txt
tensorflow3d.egg-info/top_level.txt